gocept.xmlrpcskin-2.0-py3.9-nspkg.pth
gocept/xmlrpcskin/__init__.py
gocept/xmlrpcskin/configure.zcml
gocept/xmlrpcskin/ftesting.zcml
gocept/xmlrpcskin/interfaces.py
gocept/xmlrpcskin/meta.zcml
gocept/xmlrpcskin/testing.py
gocept/xmlrpcskin/traverser.py
gocept/xmlrpcskin/zcml.py
gocept/xmlrpcskin/tests/__init__.py
gocept/xmlrpcskin/tests/test_endtoend.py
gocept/xmlrpcskin/tests/fixture/__init__.py
gocept/xmlrpcskin/tests/fixture/configure.zcml
gocept/xmlrpcskin/tests/fixture/interfaces.py
gocept/xmlrpcskin/tests/fixture/view.py
gocept.xmlrpcskin-2.0.dist-info/METADATA
gocept.xmlrpcskin-2.0.dist-info/WHEEL
gocept.xmlrpcskin-2.0.dist-info/namespace_packages.txt
gocept.xmlrpcskin-2.0.dist-info/top_level.txt
gocept.xmlrpcskin-2.0.dist-info/RECORD
