Metadata-Version: 2.1
Name: gocept.xmlrpcskin
Version: 2.0
Summary: An extension to ``zope.publisher`` that provides a ZCML directive for XML-RPC views that supports a ``layer`` parameter.
Home-page: https://github.com/zopefoundation/gocept.xmlrpcskin
Author: gocept
Author-email: zope-dev@zope.dev
License: ZPL
Keywords: zope3 xmlrpc zope.publisher
Classifier: License :: OSI Approved
Classifier: License :: OSI Approved :: Zope Public License
Classifier: Programming Language :: Python
Classifier: Programming Language :: Python :: 3
Classifier: Programming Language :: Python :: 3.7
Classifier: Programming Language :: Python :: 3.8
Classifier: Programming Language :: Python :: 3.9
Classifier: Programming Language :: Python :: 3.10
Classifier: Programming Language :: Python :: 3.11
Classifier: Development Status :: 5 - Production/Stable
Classifier: Framework :: Zope :: 3
Classifier: Intended Audience :: Developers
Classifier: Natural Language :: English
Classifier: Operating System :: OS Independent
Classifier: Topic :: Software Development
Classifier: Topic :: Software Development :: Libraries
Classifier: Topic :: Software Development :: Libraries :: Python Modules
Classifier: Topic :: Utilities
Requires-Python: >=3.7
Requires-Dist: setuptools
Requires-Dist: zope.app.publisher
Requires-Dist: zope.component[zcml]
Requires-Dist: zope.configuration
Requires-Dist: zope.interface
Requires-Dist: zope.publisher (>=3.6.0)
Requires-Dist: zope.security
Requires-Dist: zope.traversing
Provides-Extra: test
Requires-Dist: zope.app.appsetup ; extra == 'test'
Requires-Dist: zope.app.publication ; extra == 'test'
Requires-Dist: zope.app.testing ; extra == 'test'
Requires-Dist: zope.browserpage ; extra == 'test'
Requires-Dist: zope.location ; extra == 'test'
Requires-Dist: zope.principalregistry ; extra == 'test'
Requires-Dist: zope.securitypolicy ; extra == 'test'
Requires-Dist: zope.testbrowser ; extra == 'test'
Requires-Dist: zope.testrunner ; extra == 'test'
